memory_unit.v
module memory_unit (output reg [31:0] DataOut, output reg MFC,  
					input Enable, ReadWrite, input [31:0] Address, DataIn, input [1:0] wordSelector );

	reg [7:0] Mem[0:255]; //256 localizaciones de 8 bits
	//Read = 1
	//Write = 0
	always @ (Enable, ReadWrite, wordSelector, DataIn)
		begin
			case(wordSelector)
			2'b00:
				if(Enable)
				begin
					repeat(5) begin #6 MFC = 1'b1;
					#1 if(ReadWrite) 
						begin
							DataOut[31:24] = 8'h00;
							DataOut[23:16] = 8'h00;
							DataOut[15:8] = 8'h00;
							DataOut[7:0] = Mem[Address+3]; 	
							MFC = 1'b0;
						end	

					else
						begin 
							Mem[Address] = DataIn[7:0];
							MFC = 1'b0;
						end
					end
				end
				else DataOut = 32'bz;
			2'b01:
				if(Enable)
				begin
					repeat(5) begin #6 MFC = 1'b1;
					#1 if(ReadWrite)
						begin
							DataOut[31:24] = 8'h00;
							DataOut[23:16] = 8'h00;
							DataOut[15:8] = Mem[Address+2];
							DataOut[7:0] = Mem[Address+3];
							MFC = 1'b0;

						end
					else
						begin
							Mem[Address] = DataIn[7:0];
							Mem[Address + 1] = DataIn[15:8];		
							MFC = 1'b0;
						end
					end
				end
				else DataOut = 32'bz;
			2'b10:
				if(Enable)
				begin
					repeat(5) begin #6 MFC = 1'b1;
					#1 if(ReadWrite)
						begin
							DataOut[31:24] = Mem[Address];
							DataOut[23:16] = Mem[Address+1];
							DataOut[15:8] = Mem[Address+2];
							DataOut[7:0] = Mem[Address+3];	
							MFC = 1'b0;													
						end

					else
						begin
							Mem[Address] = DataIn[31:24];
							Mem[Address + 1] = DataIn[23:16];
							Mem[Address + 2] = DataIn[15:8];
							Mem[Address + 3] = DataIn[7:0];				
							MFC = 1'b0;	
						end
					end
				end
				else DataOut = 32'bz;
			default:
				if(Enable)
				begin
					repeat(5) begin #6 MFC = 1'b1;
					#1 if(ReadWrite)
						begin
							DataOut[31:24] = Mem[Address];
							DataOut[23:16] = Mem[Address+1];
							DataOut[15:8] = Mem[Address+2];
							DataOut[7:0] = Mem[Address+3];	
							MFC = 1'b0;													
						end

					else
						begin
							Mem[Address] = DataIn[31:24];
							Mem[Address + 1] = DataIn[23:16];
							Mem[Address + 2] = DataIn[15:8];
							Mem[Address + 3] = DataIn[7:0];				
							MFC = 1'b0;	
						end
					end
				end	
				else DataOut = 32'bz;
			endcase
		end
endmodule

test_ram.v
module ram_read;
	integer fd, code, i; reg[31:0] data;
	reg Enable, ReadWrite; reg[31:0] DataIn;
	reg [31:0] Address; wire [31:0] DataOut; 
	reg [1:0] wordSelector;
	wire MFC;

	reg[31:0] Inst_register, MDR;
	memory_unit ram1 (DataOut, MFC, Enable, ReadWrite, Address, DataIn, wordSelector);

	initial begin
		Address = 32'b0;
		ReadWrite = 1'b0;
		fd = $fopen("mifile.dat", "r");
		//i = 0;
		repeat(100) begin
			if (!($feof(fd))) begin	
				code = $fscanf(fd, "%b", DataIn);
				#5 begin 
					wordSelector = 01;
					Enable = 1'b1; 
					ReadWrite = 1'b0;
				end	
				#5 begin 
					wordSelector = 01;
					Enable = 1'b0;
					ReadWrite = 1'b0;
				end
				#5 begin 
					wordSelector = 01;
					Enable = 1'b1; 
					ReadWrite = 1'b1;				
				end	
				#5 begin
					Address = Address + 1; 
					wordSelector = 01;
					Enable = 1'b0; 
					ReadWrite = 1'b1;
				end	
				#5 begin 	
					wordSelector = 01;
					Enable = 1'b1; 
					ReadWrite = 1'b1;
				end	
				#5 begin 
					Address = Address + 1;
					wordSelector = 01;
					Enable = 1'b0; 
					ReadWrite = 1'b1;
				end	

			end 
		end

		$fclose(fd);
	end

	initial begin
	repeat(20) begin
		#5 		#10 ReadWrite = 1'b1;
	
		end
		$finish;
	end
	initial $monitor("Data = %h at address = %h, Enable? = %b Reading? = %b", DataOut[7:0], Address, Enable, ReadWrite);

	//initial $monitor("Data at %h = %h",Address, DataOut);
	
	initial begin
		$dumpfile("test.vcd");
		$dumpvars(0, Address, DataOut); 
	end
endmodule

test.vcd
$date
	Sun Feb  7 06:20:13 2016
$end
$version
	Icarus Verilog
$end
$timescale
	1s
$end
$scope module ram_read $end
$var reg 32 ! Address [31:0] $end
$upscope $end
$scope module ram_read $end
$var wire 32 " DataOut [31:0] $end
$upscope $end
$enddefinitions $end
#0
$dumpvars
bz "
b0 !
$end
#15
bz0100101001010101 "
#20
bz "
b1 !
#25
bz01010101xxxxxxxx "
#30
bz "
b10 !
#45
bz0000000000001101 "
#50
bz "
b11 !
#55
bz00001101xxxxxxxx "
#60
bz "
b100 !
#75
bz0001001000101011 "
#80
bz "
b101 !
#85
bz00101011xxxxxxxx "
#90
bz "
b110 !
#105
bz0010000001101010 "
#110
bz "
b111 !
#115
bz01101010xxxxxxxx "
#120
bz "
b1000 !
#135
bz0010010010010101 "
#140
bz "
b1001 !
#145
bz10010101xxxxxxxx "
#150
bz "
b1010 !
#165
bz0001100011011110 "
#170
bz "
b1011 !
#175
bz11011110xxxxxxxx "
#180
bz "
b1100 !
#195
bz0010010000101011 "
#200
bz "
b1101 !
#205
bz00101011xxxxxxxx "
#210
bz "
b1110 !
